updated_docs/__init__.py
updated_docs/update_docs.py
updated_docs-0.1.4.dist-info/LICENSE
updated_docs-0.1.4.dist-info/WHEEL
updated_docs-0.1.4.dist-info/METADATA
updated_docs-0.1.4.dist-info/RECORD
